app/__main__.py
app/config.py
app/hass.py
app/run.py
app/server.py
mseep_hass_mcp-0.1.4.dist-info/METADATA
mseep_hass_mcp-0.1.4.dist-info/WHEEL
mseep_hass_mcp-0.1.4.dist-info/entry_points.txt
mseep_hass_mcp-0.1.4.dist-info/licenses/LICENSE
mseep_hass_mcp-0.1.4.dist-info/RECORD
