Metadata-Version: 2.4
Name: mseep-hass-mcp
Version: 0.1.4
Summary: Home Assistant Model Context Protocol (MCP) server
Author-email: mseep <support@skydeck.ai>
License-File: LICENSE
Requires-Python: >=3.13
Requires-Dist: httpx>=0.27.0
Requires-Dist: mcp[cli]>=1.4.1
Provides-Extra: test
Requires-Dist: pytest-asyncio>=0.24.0; extra == 'test'
Requires-Dist: pytest>=8.3.5; extra == 'test'
